LICENSE
README.md
setup.py
pinetwig/__init__.py
pinetwig/data.py
pinetwig/functions.py
pinetwig/indicators.py
pinetwig/visualization.py
pinetwig.egg-info/PKG-INFO
pinetwig.egg-info/SOURCES.txt
pinetwig.egg-info/dependency_links.txt
pinetwig.egg-info/requires.txt
pinetwig.egg-info/top_level.txt