Metadata-Version: 2.1
Name: pinetwig
Version: 0.2.2
Summary: A pinescript-like financial data analysis and trading package
Home-page: https://github.com/AyberkAtalay0/pinetwig
Author: Ayberk ATALAY
Author-email: ayberkatalaypersonal@gmail.com
License: MIT
Keywords: python,pinetwig,financial,data,analysis,tradingview,binance,pinescript,trading,cryptocurrency,chart,candlestick,plotly,matplotlib,visualizing
Classifier: Programming Language :: Python :: 3
Classifier: License :: OSI Approved :: MIT License
Classifier: Operating System :: OS Independent
Requires-Python: >= 3.6
License-File: LICENSE
Requires-Dist: pandas
Requires-Dist: numpy
Requires-Dist: python-binance
Requires-Dist: websocket-client
Requires-Dist: websockets
Requires-Dist: datetime
Requires-Dist: plotly
Requires-Dist: matplotlib
